_hx_model_evaluation_tools/__init__.py
_hx_model_evaluation_tools/hx_feature_importances/__init__.py
_hx_model_evaluation_tools/hx_model_evaluation_and_metrics/__init__.py
_hx_model_evaluation_tools/hx_model_evaluation_and_metrics/binary_classifiers.py
_hx_model_evaluation_tools/hx_model_evaluation_and_metrics/multiclass_classifiers.py
_hx_model_evaluation_tools/hx_model_evaluation_and_metrics/regressors.py
_hx_model_evaluation_tools/hx_model_evaluation_graphics/__init__.py
_hx_model_evaluation_tools/hx_shap_tools/__init__.py
_hx_model_evaluation_tools/hx_shap_tools/dl_shap_tools.py
_hx_model_evaluation_tools/hx_shap_tools/ml_shap_tools.py
_hx_scikit_learn_tools/__init__.py
hx_deep_learning_tools/__init__.py
hx_deep_learning_tools/classifier_neural_networks/__init__.py
hx_deep_learning_tools/classifier_neural_networks/binary_neural_networks/HxDenseNeuralNetworkBinaryClassifier.py
hx_deep_learning_tools/classifier_neural_networks/binary_neural_networks/__init__.py
hx_deep_learning_tools/classifier_neural_networks/multiclass_neural_networks/HxDenseNeuralNetworkMulticlassClassifier.py
hx_deep_learning_tools/classifier_neural_networks/multiclass_neural_networks/__init__.py
hx_deep_learning_tools/dl_base_model/__init__.py
hx_deep_learning_tools/forecasting_neural_networks/__init__.py
hx_deep_learning_tools/regressor_neural_networks/HxDenseNeuralNetworkRegressor.py
hx_deep_learning_tools/regressor_neural_networks/__init__.py
hx_hyperparameters_builder/__init__.py
hx_hyperparameters_builder/abstract_hyperparameter_builder.py
hx_machine_learning_tools/__init__.py
hx_machine_learning_tools/binary_classifier_ml_models/HxCatBoostBinaryClassifier.py
hx_machine_learning_tools/binary_classifier_ml_models/HxLightGbmBinaryClassifier.py
hx_machine_learning_tools/binary_classifier_ml_models/HxRandomForestBinaryClassifier.py
hx_machine_learning_tools/binary_classifier_ml_models/HxXtremeGradientBoostingBinaryClassifier.py
hx_ml_dl_tools-1.1.0.dist-info/METADATA
hx_ml_dl_tools-1.1.0.dist-info/WHEEL
hx_ml_dl_tools-1.1.0.dist-info/top_level.txt
hx_ml_dl_tools-1.1.0.dist-info/RECORD
